<?xml version="1.0" encoding="UTF-8"?>
<thing:thing-descriptions bindingId="zwave"
  xmlns:xsi="http://www.w3.org/2001/XMLSchema-instance"
  xmlns:thing="https://openhab.org/schemas/thing-description/v1.0.0"
  xsi:schemaLocation="https://openhab.org/schemas/thing-description/v1.0.0
                      https://openhab.org/schemas/thing-description/v1.0.0">

  <thing-type id="schlage_fe599nx_00_000" listed="false">
    <label>FE599NX Connected Keypad with Lever</label>
    <description><![CDATA[
Connected Keypad with Lever<br /><h1>Overview</h1><p>Camelot style residential keypad deadbolt door lock and lever.</p> <br /><h2>Inclusion Information</h2><ol><li>Enter 6 digit Programming Code</li> <li>Wait for Schlage button to blink 3 times and 3 beeps</li> <li>Press the Schlage button and then 0</li> </ol><p>On Success the Schlage button will blink with no beeps.</p> <br /><h2>Exclusion Information</h2><ol><li>Enter 6 digit Programming Code</li> <li>Wait for Schlage button to blink 3 times and 3 beeps</li> <li>Press the Schlage button and then 0</li> </ol>
    ]]></description>
    <category>Lock</category>

    <!-- CHANNEL DEFINITIONS -->
    <channels>
      <channel id="lock_door" typeId="lock_door">
        <label>Door Lock</label>
        <properties>
          <property name="binding:*:OnOffType">COMMAND_CLASS_DOOR_LOCK</property>
        </properties>
      </channel>
      <channel id="alarm_raw" typeId="alarm_raw">
        <label>Alarm (raw)</label>
        <properties>
          <property name="binding:*:StringType">COMMAND_CLASS_ALARM</property>
        </properties>
      </channel>
      <channel id="battery-level" typeId="system.battery-level">
        <properties>
          <property name="binding:*:PercentType">COMMAND_CLASS_BATTERY</property>
        </properties>
      </channel>
    </channels>

    <!-- DEVICE PROPERTY DEFINITIONS -->
    <properties>
      <property name="vendor">Allegion</property>
      <property name="modelId">FE599NX</property>
      <property name="manufacturerId">003B</property>
      <property name="manufacturerRef">634B:504C</property>
      <property name="dbReference">403</property>
      <property name="defaultAssociations">2</property>
    </properties>

    <!-- CONFIGURATION DESCRIPTIONS -->
    <config-description>

      <!-- GROUP DEFINITIONS -->
      <parameter-group name="configuration">
        <context>setup</context>
        <label>Configuration Parameters</label>
      </parameter-group>

      <parameter-group name="association">
        <context>link</context>
        <label>Association Groups</label>
      </parameter-group>

      <!-- PARAMETER DEFINITIONS -->
      <parameter name="config_3_1" type="integer" groupName="configuration">
        <label>3: Beeper</label>
        <description>Enable/Disable keypad beep</description>
        <default>1</default>
        <options>
          <option value="0">Disable</option>
          <option value="1">Enable</option>
        </options>
      </parameter>

      <parameter name="config_4_1" type="integer" groupName="configuration">
        <label>4: Vacation Mode</label>
        <description>Enable/Disable Vacation Mode</description>
        <default>0</default>
        <options>
          <option value="0">Disable</option>
          <option value="1">Enable</option>
        </options>
      </parameter>

      <parameter name="config_5_1" type="integer" groupName="configuration">
        <label>5: Lock &amp; Leave</label>
        <description>Enable/Disable Lock &amp; Leave</description>
        <default>1</default>
        <options>
          <option value="0">Disable</option>
          <option value="1">Enable</option>
        </options>
      </parameter>

      <parameter name="config_7_1" type="integer" groupName="configuration"
                 min="0" max="255">
        <label>7: Lock Basic Set Value</label>
        <description>Byte to send with set command to devices in association group 1</description>
        <default>255</default>
        <limitToOptions>false</limitToOptions>
      </parameter>

      <!-- ASSOCIATION DEFINITIONS -->
      <parameter name="group_1" type="text" groupName="association" multiple="true">
        <label>1: Basic Set</label>
        <description>Basic Set sent with set command (configuration parameter 7)</description>
        <multipleLimit>3</multipleLimit>
      </parameter>

      <parameter name="group_2" type="text" groupName="association" multiple="true">
        <label>2: Device Status</label>
        <description>All associated commands are sent to the nodes in this group</description>
        <multipleLimit>2</multipleLimit>
      </parameter>

      <!-- STATIC DEFINITIONS -->
      <parameter name="node_id" type="integer" min="1" max="232" readOnly="true" required="true">
        <label>Node ID</label>
        <advanced>true</advanced>
      </parameter>

    </config-description>

  </thing-type>

</thing:thing-descriptions>
